tomoAO/__init__.py
tomoAO/version.py
tomoAO/IO/__init__.py
tomoAO/IO/io_functions.py
tomoAO/Reconstruction/__init__.py
tomoAO/Reconstruction/reconClassType.py
tomoAO/Reconstruction/recontructors.py
tomoAO/Simulation/__init__.py
tomoAO/Simulation/aoSystem.py
tomoAO/tools/__init__.py
tomoAO/tools/tomography_tools.py
tomoAO-0.0.6.dist-info/LICENSE
tomoAO-0.0.6.dist-info/METADATA
tomoAO-0.0.6.dist-info/WHEEL
tomoAO-0.0.6.dist-info/top_level.txt
tomoAO-0.0.6.dist-info/RECORD
