Metadata-Version: 2.1
Name: tomoAO
Version: 0.0.6
Summary: Python package with atmospheric tomography generic functions and tools
Home-page: https://github.com/SpaceODT/tomoAO
Author: SpaceODT
License: MIT
Platform: UNKNOWN
Classifier: Programming Language :: Python :: 3
Classifier: License :: OSI Approved :: MIT License
Classifier: Operating System :: OS Independent
Classifier: Intended Audience :: Science/Research
Classifier: Natural Language :: English
License-File: LICENSE
Requires-Dist: aotools
Requires-Dist: astropy
Requires-Dist: numpy
